README.md
setup.cfg
setup.py
fastiqa/__init__.py
fastiqa/all.py
fastiqa/basics.py
fastiqa/iqa_exp.py
fastiqa/label.py
fastiqa/learner.py
fastiqa/metric.py
fastiqa/qmap.py
fastiqa/util.py
fastiqa/version.py
fastiqa.egg-info/PKG-INFO
fastiqa.egg-info/SOURCES.txt
fastiqa.egg-info/dependency_links.txt
fastiqa.egg-info/requires.txt
fastiqa.egg-info/top_level.txt