Metadata-Version: 2.1
Name: fastiqa
Version: 0.6.1
Summary: fastiqa makes deep learning for image quality assessment faster and easier
Home-page: https://github.com/fastiqa/fastiqa
Author: Zhenqiang Ying
Author-email: yingzhenqiang@gmail.com
License: CC BY-NC-ND 4.0
Keywords: fastiqa,deep learning,machine learning
Platform: UNKNOWN
Classifier: Development Status :: 3 - Alpha
Classifier: Intended Audience :: Developers
Classifier: Topic :: Software Development :: Build Tools
Classifier: License :: Other/Proprietary License
Classifier: Natural Language :: English
Classifier: Programming Language :: Python :: 3
Classifier: Programming Language :: Python :: 3.7
Classifier: Programming Language :: Python :: 3.6
